moonroof/__init__.py
moonroof/request.py
moonroof/thread.py
moonroof/middleware/__init__.py
moonroof/middleware/general_middleware.py
moonroof/middleware/sql_middleware.py
moonroof/middleware/time_middleware.py
moonroof-0.0.5.dist-info/LICENSE
moonroof-0.0.5.dist-info/METADATA
moonroof-0.0.5.dist-info/WHEEL
moonroof-0.0.5.dist-info/top_level.txt
moonroof-0.0.5.dist-info/RECORD
