Metadata-Version: 2.1
Name: moonroof
Version: 0.0.5
Summary: Client library for moonroof
Home-page: https://github.com/inputlogic/moonroof-django
Author: Input Logic
Author-email: adriaan@inputlogic.ca
License: UNKNOWN
Platform: UNKNOWN
Classifier: Development Status :: 1 - Planning
Classifier: Framework :: Django
Classifier: Topic :: System :: Monitoring
Classifier: Programming Language :: Python :: 3
Classifier: License :: OSI Approved :: MIT License
Classifier: Operating System :: OS Independent
Requires-Python: >=3.6
Requires-Dist: requests
